gitlab_time_report/__init__.py
gitlab_time_report/bar_chart.py
gitlab_time_report/cake_chart.py
gitlab_time_report/chart.py
gitlab_time_report/gitlab_project.py
gitlab_time_report/out.md
gitlab_time_report/template_renderer.py
gitlab_time_report/time_report.py
gitlab_time_report-1.0.dist-info/LICENSE.md
gitlab_time_report-1.0.dist-info/WHEEL
gitlab_time_report-1.0.dist-info/METADATA
gitlab_time_report-1.0.dist-info/RECORD
